{"skeleton":{"hash":"dXvYKNSQid9aoV4JJAYYKdvXAO4","spine":"3.3.07","width":231,"height":227,"images":""},"bones":[{"name":"root"},{"name":"body","parent":"root","length":77,"rotation":89.99,"x":1.28,"y":113.29}],"slots":[{"name":"blob_body","bone":"body","attachment":"blob_normal"}],"skins":{"default":{"blob_body":{"blob_mouth_happy":{"type":"linkedmesh","parent":"blob_normal","width":231,"height":227},"blob_mouth_open":{"type":"linkedmesh","parent":"blob_normal","width":231,"height":227},"blob_mouth_sad":{"type":"linkedmesh","parent":"blob_normal","width":231,"height":227},"blob_normal":{"type":"mesh","uvs":[1,1,0,1,0,0,1,0,0.63059,0.53529],"triangles":[4,2,3,1,2,4,4,3,0,1,4,0],"vertices":[-113.49,-115.5,-113.5,115.49,113.49,115.5,113.5,-115.49,-8.01,-30.16],"hull":4,"edges":[0,2,2,4,4,6,0,6],"width":231,"height":227}}}},"animations":{"eat":{"slots":{"blob_body":{"attachment":[{"time":0,"name":"blob_mouth_happy"},{"time":0.5333,"name":"blob_mouth_open"},{"time":0.6666,"name":"blob_normal"},{"time":0.8,"name":"blob_mouth_open"},{"time":0.9333,"name":"blob_normal"},{"time":1.0666,"name":"blob_mouth_open"},{"time":1.2,"name":"blob_normal"},{"time":1.2666,"name":"blob_mouth_happy"}]}},"bones":{"root":{"rotate":[{"time":0,"angle":0,"curve":"stepped"},{"time":1.2666,"angle":0}],"translate":[{"time":0,"x":0,"y":0,"curve":"stepped"},{"time":1.2666,"x":0,"y":0}]},"body":{"rotate":[{"time":0,"angle":0,"curve":"stepped"},{"time":1.2666,"angle":0}],"translate":[{"time":0,"x":0,"y":0},{"time":0.1333,"x":29.67,"y":0,"curve":"stepped"},{"time":0.4,"x":29.67,"y":0},{"time":1.2666,"x":0,"y":0}]}},"deform":{"default":{"blob_body":{"blob_normal":[{"time":0},{"time":0.1333,"vertices":[2.11999,21.20001,2.11999,21.20001,0,-5.85189,0,-27.55996],"curve":"stepped"},{"time":0.4,"vertices":[2.11999,21.20001,2.11999,21.20001,0,-5.85189,0,-27.55996]},{"time":0.5333,"vertices":[2.11999,21.20001,2.11999,21.20001,-2.11996,-21.19992,-12.72003,-27.55996,-16.95993,-4.24]},{"time":0.6666,"vertices":[2.11999,21.20001,2.11999,21.20001,0,-27.55996,0,-27.55996]},{"time":0.8,"offset":1,"vertices":[6.35987,2.11999,21.20001,0,-27.55996,0,-2.12005,10.60003,4.24004]},{"time":0.9333,"vertices":[2.11999,21.20001,2.11999,21.20001,10.59994,-12.71999,0,-27.55996,-19.08001,-6.35995]},{"time":1.2,"vertices":[2.11999,21.20001,2.11999,21.20001,0,-27.55996,0,-27.55996]},{"time":1.2666}],"blob_mouth_happy":[{"time":0.4,"vertices":[2.11999,21.20001,2.11999,21.20001,0,-5.85189,0,-27.55996]}]}}}},"idle":{"deform":{"default":{"blob_body":{"blob_normal":[{"time":0},{"time":0.2666,"vertices":[3.66899,19.58883,3.66899,-9.80487,17.91201,0,17.912,0,29.56802,-2.11198]},{"time":0.4},{"time":0.6666,"offset":1,"vertices":[-14.83999,0,16.95996,-25.43994,16.95996,-25.43995,-14.83999,-26.39997,-2.11199]},{"time":1}]}}}},"walk":{"slots":{"blob_body":{"attachment":[{"time":0,"name":"blob_normal"},{"time":0.6666,"name":"blob_normal"}]}},"bones":{"body":{"rotate":[{"time":0,"angle":0},{"time":0.2,"angle":12.47},{"time":0.3333,"angle":-7.72,"curve":"stepped"},{"time":0.4666,"angle":-7.72},{"time":0.6666,"angle":0}],"translate":[{"time":0,"x":0,"y":0},{"time":0.2,"x":-6.44,"y":0},{"time":0.2666,"x":8.27,"y":11.6},{"time":0.3333,"x":22.98,"y":0,"curve":"stepped"},{"time":0.4666,"x":22.98,"y":0},{"time":0.6666,"x":0,"y":0}]},"root":{"rotate":[{"time":0,"angle":0}],"translate":[{"time":0,"x":0,"y":0}]}},"deform":{"default":{"blob_body":{"blob_normal":[{"time":0},{"time":0.2,"vertices":[0.26702,13.14257,0,0,-14.12264,1.804,-9.09976,12.57436,0,11.60098]},{"time":0.2666,"vertices":[5.39191,8.93358,11.21064,21.46722,-13.01351,-18.20286,-2.7213,-11.85006,3.86697,0.64448]},{"time":0.3333,"vertices":[10.02675,-7.27882,0,0,2.70915,-29.55107,0,0,7.73394,-10.31201],"curve":"stepped"},{"time":0.4666,"vertices":[10.02675,-7.27882,0,0,2.70915,-29.55107,0,0,7.73394,-10.31201]},{"time":0.6,"offset":8,"vertices":[-11.60102,-3.86701]},{"time":0.6666}]}}}}}}